topologika.cp311-win_amd64.pyd
topologika-2022.12.dist-info/LICENSE
topologika-2022.12.dist-info/METADATA
topologika-2022.12.dist-info/WHEEL
topologika-2022.12.dist-info/top_level.txt
topologika-2022.12.dist-info/RECORD
